MANIFEST.in
README.rst
setup.py
fuzzybit/__init__.py
fuzzybit/fuzzybit.py
fuzzybit.egg-info/PKG-INFO
fuzzybit.egg-info/SOURCES.txt
fuzzybit.egg-info/dependency_links.txt
fuzzybit.egg-info/requires.txt
fuzzybit.egg-info/top_level.txt
fuzzybit.egg-info/zip-safe