Metadata-Version: 1.1
Name: fuzzybit
Version: 0.2.0
Summary: Fuzzy bit library
Home-page: https://github.com/tmfink/fuzzybit
Author: Travis Finkenauer
Author-email: tmfink@umich.edu
License: GPLv3
Download-URL: https://github.com/tmfink/fuzzybit/tarball/master
Keywords: fuzzy bit integer entropy
Platform: UNKNOWN
Classifier: Development Status :: 3 - Alpha
Classifier: License :: OSI Approved :: GNU General Public License v3 (GPLv3)
Classifier: Programming Language :: Python :: 2.5
Classifier: Programming Language :: Python :: 2.6
Classifier: Programming Language :: Python :: 2.7
Classifier: Programming Language :: Python :: 3.2
Classifier: Programming Language :: Python :: 3.3
Classifier: Programming Language :: Python :: 3.4
Classifier: Programming Language :: Python :: 3.5
Classifier: Topic :: Security
Classifier: Topic :: Utilities
